mujoco_lidar/__init__.py
mujoco_lidar/lidar_wrapper.py
mujoco_lidar/mj_lidar_utils.py
mujoco_lidar/scan_gen.py
mujoco_lidar/scan_gen_livox_ti.py
mujoco_lidar/scan_mode/HAP.npy
mujoco_lidar/scan_mode/avia.npy
mujoco_lidar/scan_mode/horizon.npy
mujoco_lidar/scan_mode/mid360.npy
mujoco_lidar/scan_mode/mid40.npy
mujoco_lidar/scan_mode/mid70.npy
mujoco_lidar/scan_mode/tele.npy
mujoco_lidar-0.2.6.dist-info/licenses/LICENSE
mujoco_lidar-0.2.6.dist-info/METADATA
mujoco_lidar-0.2.6.dist-info/WHEEL
mujoco_lidar-0.2.6.dist-info/top_level.txt
mujoco_lidar-0.2.6.dist-info/RECORD
