Metadata-Version: 2.4
Name: mujoco_lidar
Version: 0.2.6
Summary: A LiDAR sensor designed for MuJoCo
Author-email: Yufei Jia <jyf23@mails.tsinghua.edu.cn>
License: MIT
Project-URL: Homepage, https://github.com/TATP-233/MuJoCo-LiDAR.git
Project-URL: Repository, https://github.com/TATP-233/MuJoCo-LiDAR.git
Classifier: Programming Language :: Python :: 3
Classifier: License :: OSI Approved :: MIT License
Classifier: Operating System :: OS Independent
Requires-Python: >=3.8
License-File: LICENSE
Requires-Dist: numpy>=1.20.0
Requires-Dist: mujoco>=3.2.0
Requires-Dist: scipy
Requires-Dist: pynput
Requires-Dist: matplotlib
Requires-Dist: zhplot
Provides-Extra: taichi
Requires-Dist: taichi>=1.6.0; extra == "taichi"
Requires-Dist: tibvh>=0.1.2; extra == "taichi"
Provides-Extra: jax
Requires-Dist: jax[cuda12]; extra == "jax"
Dynamic: license-file
